README.rst
setup.py
seagull/__init__.py
seagull.egg-info/PKG-INFO
seagull.egg-info/SOURCES.txt
seagull.egg-info/dependency_links.txt
seagull.egg-info/top_level.txt
seagull/font/__init__.py
seagull/font/_cocoa.py
seagull/font/freetype2.py
seagull/font/utils.py
seagull/opengl/__init__.py
seagull/opengl/gl.py
seagull/opengl/utils.py
seagull/scenegraph/__init__.py
seagull/scenegraph/_common.py
seagull/scenegraph/paint.py
seagull/scenegraph/transform.py
seagull/scenegraph/element/__init__.py
seagull/scenegraph/element/_path.py
seagull/scenegraph/element/circle.py
seagull/scenegraph/element/ellipse.py
seagull/scenegraph/element/group.py
seagull/scenegraph/element/image.py
seagull/scenegraph/element/line.py
seagull/scenegraph/element/path.py
seagull/scenegraph/element/polygon.py
seagull/scenegraph/element/polyline.py
seagull/scenegraph/element/rectangle.py
seagull/scenegraph/element/text.py
seagull/scenegraph/element/use.py
seagull/xml/__init__.py
seagull/xml/parser.py
seagull/xml/serializer.py