Metadata-Version: 1.1
Name: seagull
Version: 0.1
Summary: 2D scene graph based on SVG with OpenGL backend
Home-page: http://bitbucket.org/rndblnch/seagull
Author: Renaud Blanch
Author-email: rb@rndblnch.org
License: GPLv3+
Platform: UNKNOWN
Classifier: License :: OSI Approved :: GNU General Public License v3 or later (GPLv3+)
Classifier: Programming Language :: Python :: 3.3
Classifier: Topic :: Software Development :: Libraries :: Python Modules
Classifier: Topic :: Multimedia :: Graphics
